vartulz_compliance_sdk/__init__.py
vartulz_compliance_sdk/api_client.py
vartulz_compliance_sdk/configuration.py
vartulz_compliance_sdk/exceptions.py
vartulz_compliance_sdk/rest.py
vartulz_compliance_sdk/schemas.py
vartulz_compliance_sdk/apis/__init__.py
vartulz_compliance_sdk/apis/path_to_api.py
vartulz_compliance_sdk/apis/tag_to_api.py
vartulz_compliance_sdk/apis/paths/__init__.py
vartulz_compliance_sdk/apis/paths/v1_aadhar_delete_aadhar.py
vartulz_compliance_sdk/apis/paths/v1_aadhar_get_all_aadhar.py
vartulz_compliance_sdk/apis/paths/v1_aadhar_send_otp.py
vartulz_compliance_sdk/apis/paths/v1_aadhar_submit_otp.py
vartulz_compliance_sdk/apis/paths/v1_bank_add_verify.py
vartulz_compliance_sdk/apis/paths/v1_bank_delete_bank.py
vartulz_compliance_sdk/apis/paths/v1_bank_get_all.py
vartulz_compliance_sdk/apis/paths/v1_barcode_generatre_barcode.py
vartulz_compliance_sdk/apis/paths/v1_barcode_get_aadhar_details.py
vartulz_compliance_sdk/apis/paths/v1_barcode_get_bank_details.py
vartulz_compliance_sdk/apis/paths/v1_barcode_get_electricity_details.py
vartulz_compliance_sdk/apis/paths/v1_barcode_get_gstin_details.py
vartulz_compliance_sdk/apis/paths/v1_barcode_get_gstin_preference_details_gstin.py
vartulz_compliance_sdk/apis/paths/v1_barcode_get_gstin_status_gstin.py
vartulz_compliance_sdk/apis/paths/v1_barcode_get_gstin_track_details_gstin.py
vartulz_compliance_sdk/apis/paths/v1_barcode_get_iec_details.py
vartulz_compliance_sdk/apis/paths/v1_barcode_get_master_details.py
vartulz_compliance_sdk/apis/paths/v1_barcode_get_pan_details.py
vartulz_compliance_sdk/apis/paths/v1_barcode_get_signatory_details.py
vartulz_compliance_sdk/apis/paths/v1_barcode_share_barcode.py
vartulz_compliance_sdk/apis/paths/v1_biller_get_all_biller.py
vartulz_compliance_sdk/apis/paths/v1_biller_get_all_bystate_state.py
vartulz_compliance_sdk/apis/paths/v1_biller_get_all_state.py
vartulz_compliance_sdk/apis/paths/v1_case_admin_get_all_case.py
vartulz_compliance_sdk/apis/paths/v1_case_create_new.py
compliance_sdk-3.0.0.dist-info/METADATA
compliance_sdk-3.0.0.dist-info/WHEEL
compliance_sdk-3.0.0.dist-info/top_level.txt
compliance_sdk-3.0.0.dist-info/RECORD
