Metadata-Version: 2.1
Name: compliance_sdk
Version: 3.0.0
Summary: e-KYC API client for BALAJI MARILINE PRIVATE LIMITED
Home-page: https://github.com/gautam199429/balaji-sdk
Author: BALAJI MARILINE PRIVATE LIMITED
Author-email: gautam@balajimariline.com
License: Proprietary :: BALAJI MARILINE PRIVATE LIMITED
Keywords: OpenAPI,e-KYC,KYC,API Client,BALAJI
Classifier: Development Status :: 4 - Beta
Classifier: Intended Audience :: Developers
Classifier: Programming Language :: Python :: 3
Classifier: Operating System :: OS Independent
Classifier: License :: Other/Proprietary License
Requires-Python: >=3.7
Requires-Dist: certifi >=14.5.14
Requires-Dist: frozendict ~=2.3.4
Requires-Dist: python-dateutil ~=2.7.0
Requires-Dist: setuptools >=21.0.0
Requires-Dist: typing-extensions ~=4.3.0
Requires-Dist: urllib3 ~=1.26.7
